django_wechat/__init__.py
django_wechat/admin.py
django_wechat/models.py
django_wechat/tests.py
django_wechat/views.py
django_wechat/migrations/__init__.py
django_wechat-0.1a1.dist-info/METADATA
django_wechat-0.1a1.dist-info/RECORD
django_wechat-0.1a1.dist-info/WHEEL
django_wechat-0.1a1.dist-info/entry_points.txt
django_wechat-0.1a1.dist-info/top_level.txt
django_wechat-0.1a1.dist-info/zip-safe
